pyams_chat/__init__.py
pyams_chat/client.py
pyams_chat/include.py
pyams_chat/interfaces.py
pyams_chat/message.py
pyams_chat/api/__init__.py
pyams_chat/doctests/README.rst
pyams_chat/handler/__init__.py
pyams_chat/handler/login.py
pyams_chat/locales/pyams_chat.pot
pyams_chat/locales/fr/LC_MESSAGES/pyams_chat.mo
pyams_chat/locales/fr/LC_MESSAGES/pyams_chat.po
pyams_chat/tests/__init__.py
pyams_chat/tests/test_utilsdocs.py
pyams_chat/tests/test_utilsdocstrings.py
pyams_chat/zmi/__init__.py
pyams_chat/zmi/worker.py
pyams_chat/zmi/resources/js/chat-sw.js
pyams_chat/zmi/resources/js/pyams_chat.js
pyams_chat/zmi/resources/js/pyams_chat.min.js
pyams_chat/zmi/viewlet/__init__.py
pyams_chat/zmi/viewlet/interfaces.py
pyams_chat/zmi/viewlet/notifications.py
pyams_chat/zmi/viewlet/templates/notifications.pt
pyams_chat-2.1.4.dist-info/LICENSE
pyams_chat-2.1.4.dist-info/METADATA
pyams_chat-2.1.4.dist-info/WHEEL
pyams_chat-2.1.4.dist-info/entry_points.txt
pyams_chat-2.1.4.dist-info/namespace_packages.txt
pyams_chat-2.1.4.dist-info/top_level.txt
pyams_chat-2.1.4.dist-info/RECORD
